seaport/__init__.py
seaport/_autocomplete/seaport.bash
seaport/_autocomplete/seaport.fish
seaport/_autocomplete/seaport.zsh
seaport/_click_functions.py
seaport/_clipboard/__init__.py
seaport/_clipboard/additional.py
seaport/_clipboard/checks.py
seaport/_clipboard/clipboard.py
seaport/_clipboard/format.py
seaport/_clipboard/portfile/__init__.py
seaport/_clipboard/portfile/checksums.py
seaport/_clipboard/portfile/portfile_numbers.py
seaport/_clipboard/user.py
seaport/_init.py
seaport/_pull_request/__init__.py
seaport/_pull_request/clone.py
seaport/_pull_request/portfile.py
seaport/_pull_request/pull_request.py
seaport/portfile.py
seaport/py.typed
seaport-0.10.1.dist-info/LICENSE
seaport-0.10.1.dist-info/METADATA
seaport-0.10.1.dist-info/WHEEL
seaport-0.10.1.dist-info/entry_points.txt
seaport-0.10.1.dist-info/RECORD
