Metadata-Version: 2.1
Name: seaport
Version: 0.10.1
Summary: The modern MacPorts portfile updater
Home-page: https://seaport.rtfd.io/
License: BSD-3-Clause
Keywords: MacPorts,Port,Bump,Checksums
Author: harens
Author-email: harensdeveloper@gmail.com
Maintainer: harens
Maintainer-email: harensdeveloper@gmail.com
Requires-Python: >=3.7,<4.0
Classifier: Intended Audience :: Developers
Classifier: License :: OSI Approved :: BSD License
Classifier: Natural Language :: English
Classifier: Operating System :: OS Independent
Classifier: Programming Language :: Python :: 3
Classifier: Programming Language :: Python :: 3.7
Classifier: Programming Language :: Python :: 3.8
Classifier: Programming Language :: Python :: 3.9
Classifier: Programming Language :: Python :: 3.10
Classifier: Programming Language :: Python :: 3.11
Classifier: Typing :: Typed
Requires-Dist: beartype (>=0.12,<0.15)
Requires-Dist: click (>=8.1.3,<9.0.0)
Requires-Dist: typing-extensions (>=4.0.0,<5.0) ; python_version < "3.9"
Project-URL: Bug Tracker, https://github.com/harens/seaport/issues
Project-URL: Documentation, https://seaport.rtfd.io/
Project-URL: Repository, https://github.com/harens/seaport
